zulu/__init__.py
zulu/api.py
zulu/delta.py
zulu/helpers.py
zulu/parser.py
zulu/timer.py
zulu/zulu.py
zulu-2.0.1.dist-info/AUTHORS.rst
zulu-2.0.1.dist-info/LICENSE.rst
zulu-2.0.1.dist-info/METADATA
zulu-2.0.1.dist-info/WHEEL
zulu-2.0.1.dist-info/top_level.txt
zulu-2.0.1.dist-info/RECORD
