Metadata-Version: 2.1
Name: zulu
Version: 2.0.1
Summary: A drop-in replacement for native datetimes that embraces UTC
Home-page: https://github.com/dgilland/zulu
Author: Derrick Gilland
Author-email: dgilland@gmail.com
License: MIT License
Keywords: zulu date time datetime timedelta utc parser
Classifier: Development Status :: 5 - Production/Stable
Classifier: License :: OSI Approved :: MIT License
Classifier: Intended Audience :: Developers
Classifier: Operating System :: OS Independent
Classifier: Programming Language :: Python
Classifier: Programming Language :: Python :: 3
Classifier: Programming Language :: Python :: 3.7
Classifier: Programming Language :: Python :: 3.8
Classifier: Programming Language :: Python :: 3.9
Classifier: Programming Language :: Python :: 3.10
Classifier: Programming Language :: Python :: 3.11
Classifier: Programming Language :: Python :: 3.12
Classifier: Topic :: Software Development :: Libraries
Classifier: Topic :: Software Development :: Libraries :: Python Modules
Classifier: Topic :: Utilities
Requires-Python: >=3.6
License-File: LICENSE.rst
License-File: AUTHORS.rst
Requires-Dist: Babel>=2.3.4
Requires-Dist: iso8601>=0.1.11
Requires-Dist: python-dateutil>=2.6.0
Requires-Dist: pytimeparse>=1.1.5
Provides-Extra: dev
Requires-Dist: black; extra == "dev"
Requires-Dist: build; extra == "dev"
Requires-Dist: coverage; extra == "dev"
Requires-Dist: docformatter; extra == "dev"
Requires-Dist: flake8; extra == "dev"
Requires-Dist: flake8-black; extra == "dev"
Requires-Dist: flake8-bugbear; extra == "dev"
Requires-Dist: flake8-isort; extra == "dev"
Requires-Dist: furo; extra == "dev"
Requires-Dist: importlib_metadata<5; python_version == "3.7" and extra == "dev"
Requires-Dist: invoke; extra == "dev"
Requires-Dist: isort; extra == "dev"
Requires-Dist: pylint; extra == "dev"
Requires-Dist: pytest; extra == "dev"
Requires-Dist: pytest-cov; extra == "dev"
Requires-Dist: pytz; extra == "dev"
Requires-Dist: sphinx; extra == "dev"
Requires-Dist: tox; extra == "dev"
Requires-Dist: twine; extra == "dev"
Requires-Dist: wheel; extra == "dev"
